{
  "id": "c8b75117-7a2c-45b9-b5d5-d0dccab7a91f",
  "revision": 0,
  "last_node_id": 171,
  "last_link_id": 209,
  "nodes": [
    {
      "id": 118,
      "type": "Label (rgthree)",
      "pos": [
        1664.68505859375,
        -1219.1610107421875
      ],
      "size": [
        690.943359375,
        36
      ],
      "flags": {
        "allow_interaction": true
      },
      "order": 0,
      "mode": 0,
      "inputs": [],
      "outputs": [],
      "title": "https://www.youtube.com/@sunleyan_2021",
      "properties": {
        "fontSize": 36,
        "fontFamily": "Arial",
        "fontColor": "#ffffff",
        "textAlign": "left",
        "backgroundColor": "transparent",
        "padding": 0,
        "borderRadius": 0,
        "widget_ue_connectable": {}
      },
      "color": "#fff0",
      "bgcolor": "#fff0"
    },
    {
      "id": 119,
      "type": "Label (rgthree)",
      "pos": [
        1325.7381591796875,
        -1145.500244140625
      ],
      "size": [
        408.076171875,
        36
      ],
      "flags": {
        "allow_interaction": true
      },
      "order": 1,
      "mode": 0,
      "inputs": [],
      "outputs": [],
      "title": "bilibli：有趣的80后程序员",
      "properties": {
        "fontSize": 36,
        "fontFamily": "Arial",
        "fontColor": "#ffffff",
        "textAlign": "left",
        "backgroundColor": "transparent",
        "padding": 0,
        "borderRadius": 0,
        "widget_ue_connectable": {}
      },
      "color": "#fff0",
      "bgcolor": "#fff0"
    },
    {
      "id": 120,
      "type": "Label (rgthree)",
      "pos": [
        1323.974853515625,
        -1219.7181396484375
      ],
      "size": [
        306.123046875,
        36
      ],
      "flags": {
        "allow_interaction": true
      },
      "order": 2,
      "mode": 0,
      "inputs": [],
      "outputs": [],
      "title": "youtube：AI老腊肉",
      "properties": {
        "fontSize": 36,
        "fontFamily": "Arial",
        "fontColor": "#ffffff",
        "textAlign": "left",
        "backgroundColor": "transparent",
        "padding": 0,
        "borderRadius": 0,
        "widget_ue_connectable": {}
      },
      "color": "#fff0",
      "bgcolor": "#fff0"
    },
    {
      "id": 121,
      "type": "Label (rgthree)",
      "pos": [
        1327.5889892578125,
        -1059.7745361328125
      ],
      "size": [
        400.04296875,
        36
      ],
      "flags": {
        "allow_interaction": true
      },
      "order": 3,
      "mode": 0,
      "inputs": [],
      "outputs": [],
      "title": "抖音：有趣的80后程序员",
      "properties": {
        "fontSize": 36,
        "fontFamily": "Arial",
        "fontColor": "#ffffff",
        "textAlign": "left",
        "backgroundColor": "transparent",
        "padding": 0,
        "borderRadius": 0,
        "widget_ue_connectable": {}
      },
      "color": "#fff0",
      "bgcolor": "#fff0"
    },
    {
      "id": 122,
      "type": "Label (rgthree)",
      "pos": [
        1328.071044921875,
        -974.3994750976562
      ],
      "size": [
        288,
        36
      ],
      "flags": {
        "allow_interaction": true
      },
      "order": 4,
      "mode": 0,
      "inputs": [],
      "outputs": [],
      "title": "工作流下载地址：",
      "properties": {
        "fontSize": 36,
        "fontFamily": "Arial",
        "fontColor": "#ffffff",
        "textAlign": "left",
        "backgroundColor": "transparent",
        "padding": 0,
        "borderRadius": 0,
        "widget_ue_connectable": {}
      },
      "color": "#fff0",
      "bgcolor": "#fff0"
    },
    {
      "id": 123,
      "type": "Label (rgthree)",
      "pos": [
        1643.7666015625,
        -971.1257934570312
      ],
      "size": [
        806.484375,
        36
      ],
      "flags": {
        "allow_interaction": true
      },
      "order": 5,
      "mode": 0,
      "inputs": [],
      "outputs": [],
      "title": "https://github.com/amao2001/ganloss-latent-space",
      "properties": {
        "fontSize": 36,
        "fontFamily": "Arial",
        "fontColor": "#ffffff",
        "textAlign": "left",
        "backgroundColor": "transparent",
        "padding": 0,
        "borderRadius": 0,
        "widget_ue_connectable": {}
      },
      "color": "#fff0",
      "bgcolor": "#fff0"
    },
    {
      "id": 124,
      "type": "Label (rgthree)",
      "pos": [
        1763.0946044921875,
        -1148.11865234375
      ],
      "size": [
        590.37890625,
        36
      ],
      "flags": {
        "allow_interaction": true
      },
      "order": 6,
      "mode": 0,
      "inputs": [],
      "outputs": [],
      "title": "https://space.bilibili.com/1078072406",
      "properties": {
        "fontSize": 36,
        "fontFamily": "Arial",
        "fontColor": "#ffffff",
        "textAlign": "left",
        "backgroundColor": "transparent",
        "padding": 0,
        "borderRadius": 0,
        "widget_ue_connectable": {}
      },
      "color": "#fff0",
      "bgcolor": "#fff0"
    },
    {
      "id": 141,
      "type": "SetNode",
      "pos": [
        313.83721923828125,
        -391.0225830078125
      ],
      "size": [
        214.01412963867188,
        61.00347137451172
      ],
      "flags": {},
      "order": 27,
      "mode": 0,
      "inputs": [
        {
          "label": "INT",
          "name": "INT",
          "type": "INT",
          "link": 177
        }
      ],
      "outputs": [
        {
          "label": "*",
          "name": "*",
          "type": "*"
        }
      ],
      "title": "Set_widht",
      "properties": {
        "previousName": "widht",
        "widget_ue_connectable": {}
      },
      "widgets_values": [
        "widht"
      ],
      "color": "#1b4669",
      "bgcolor": "#29699c"
    },
    {
      "id": 142,
      "type": "SetNode",
      "pos": [
        318.83721923828125,
        -251.55218505859375
      ],
      "size": [
        210,
        58
      ],
      "flags": {},
      "order": 29,
      "mode": 0,
      "inputs": [
        {
          "label": "INT",
          "name": "INT",
          "type": "INT",
          "link": 178
        }
      ],
      "outputs": [
        {
          "label": "*",
          "name": "*",
          "type": "*"
        }
      ],
      "title": "Set_height",
      "properties": {
        "previousName": "height",
        "widget_ue_connectable": {}
      },
      "widgets_values": [
        "height"
      ],
      "color": "#1b4669",
      "bgcolor": "#29699c"
    },
    {
      "id": 143,
      "type": "SetNode",
      "pos": [
        319.8232116699219,
        -113.08541107177734
      ],
      "size": [
        210,
        58
      ],
      "flags": {},
      "order": 30,
      "mode": 0,
      "inputs": [
        {
          "label": "INT",
          "name": "INT",
          "type": "INT",
          "link": 179
        }
      ],
      "outputs": [
        {
          "label": "*",
          "name": "*",
          "type": "*"
        }
      ],
      "title": "Set_frames",
      "properties": {
        "previousName": "frames",
        "widget_ue_connectable": {}
      },
      "widgets_values": [
        "frames"
      ],
      "color": "#1b4669",
      "bgcolor": "#29699c"
    },
    {
      "id": 149,
      "type": "VHS_VideoCombine",
      "pos": [
        1485.7332763671875,
        616.4628295898438
      ],
      "size": [
        276.7795104980469,
        825.1403198242188
      ],
      "flags": {},
      "order": 40,
      "mode": 0,
      "inputs": [
        {
          "label": "images",
          "name": "images",
          "type": "IMAGE",
          "link": 184
        },
        {
          "label": "audio",
          "name": "audio",
          "shape": 7,
          "type": "AUDIO"
        },
        {
          "label": "meta_batch",
          "name": "meta_batch",
          "shape": 7,
          "type": "VHS_BatchManager"
        },
        {
          "label": "vae",
          "name": "vae",
          "shape": 7,
          "type": "VAE"
        },
        {
          "label": "frame_rate",
          "name": "frame_rate",
          "type": "FLOAT",
          "widget": {
            "name": "frame_rate"
          }
        },
        {
          "label": "loop_count",
          "name": "loop_count",
          "type": "INT",
          "widget": {
            "name": "loop_count"
          }
        },
        {
          "label": "filename_prefix",
          "name": "filename_prefix",
          "type": "STRING",
          "widget": {
            "name": "filename_prefix"
          }
        },
        {
          "label": "format",
          "name": "format",
          "type": "COMBO",
          "widget": {
            "name": "format"
          }
        },
        {
          "label": "pingpong",
          "name": "pingpong",
          "type": "BOOLEAN",
          "widget": {
            "name": "pingpong"
          }
        },
        {
          "label": "save_output",
          "name": "save_output",
          "type": "BOOLEAN",
          "widget": {
            "name": "save_output"
          }
        },
        {
          "label": "no_preview",
          "name": "no_preview",
          "shape": 7,
          "type": "BOOLEAN",
          "widget": {
            "name": "no_preview"
          }
        }
      ],
      "outputs": [
        {
          "label": "Filenames",
          "name": "Filenames",
          "type": "VHS_FILENAMES"
        }
      ],
      "properties": {
        "Node name for S&R": "VHS_VideoCombine",
        "widget_ue_connectable": {}
      },
      "widgets_values": {
        "frame_rate": 16,
        "loop_count": 0,
        "filename_prefix": "AnimateDiff",
        "format": "video/h264-mp4.json",
        "pix_fmt": "yuv420p",
        "crf": 19,
        "save_metadata": true,
        "trim_to_audio": false,
        "pingpong": false,
        "save_output": false,
        "no_preview": false,
        "videopreview": {
          "paused": false,
          "hidden": false,
          "params": {
            "score": "0",
            "filename": "AnimateDiff_00001_p86_ldpvr_1763620409.mp4",
            "workflow": "AnimateDiff_00001_p86.png",
            "fullpath": "/data/ComfyUI/personal/445aa9a89d7fa5567450f91c998092da/temp/AnimateDiff_00001_p86.mp4",
            "format": "video/h264-mp4.json",
            "subfolder": "",
            "label": "Normal",
            "type": "temp",
            "frame_rate": 16
          }
        }
      }
    },
    {
      "id": 29,
      "type": "WanVideoDecode",
      "pos": [
        2918.236572265625,
        -400.8967590332031
      ],
      "size": [
        315,
        198
      ],
      "flags": {},
      "order": 44,
      "mode": 0,
      "inputs": [
        {
          "label": "vae",
          "name": "vae",
          "type": "WANVAE",
          "link": 28
        },
        {
          "label": "samples",
          "name": "samples",
          "type": "LATENT",
          "link": 27
        },
        {
          "label": "enable_vae_tiling",
          "name": "enable_vae_tiling",
          "type": "BOOLEAN",
          "widget": {
            "name": "enable_vae_tiling"
          }
        },
        {
          "label": "tile_x",
          "name": "tile_x",
          "type": "INT",
          "widget": {
            "name": "tile_x"
          }
        },
        {
          "label": "tile_y",
          "name": "tile_y",
          "type": "INT",
          "widget": {
            "name": "tile_y"
          }
        },
        {
          "label": "tile_stride_x",
          "name": "tile_stride_x",
          "type": "INT",
          "widget": {
            "name": "tile_stride_x"
          }
        },
        {
          "label": "tile_stride_y",
          "name": "tile_stride_y",
          "type": "INT",
          "widget": {
            "name": "tile_stride_y"
          }
        },
        {
          "label": "normalization",
          "name": "normalization",
          "shape": 7,
          "type": "COMBO",
          "widget": {
            "name": "normalization"
          }
        }
      ],
      "outputs": [
        {
          "label": "images",
          "name": "images",
          "type": "IMAGE",
          "slot_index": 0,
          "links": [
            29
          ]
        }
      ],
      "properties": {
        "Node name for S&R": "WanVideoDecode",
        "cnr_id": "ComfyUI-WanVideoWrapper",
        "ver": "d9b1f4d1a5aea91d101ae97a54714a5861af3f50",
        "widget_ue_connectable": {}
      },
      "widgets_values": [
        false,
        272,
        272,
        144,
        128,
        "default"
      ],
      "color": "#322",
      "bgcolor": "#533"
    },
    {
      "id": 108,
      "type": "ImageResizeKJv2",
      "pos": [
        974.6478881835938,
        -394.61199951171875
      ],
      "size": [
        315,
        336
      ],
      "flags": {},
      "order": 28,
      "mode": 0,
      "inputs": [
        {
          "label": "image",
          "name": "image",
          "type": "IMAGE",
          "link": 138
        },
        {
          "label": "mask",
          "name": "mask",
          "shape": 7,
          "type": "MASK"
        },
        {
          "label": "width",
          "name": "width",
          "type": "INT",
          "widget": {
            "name": "width"
          },
          "link": 159
        },
        {
          "label": "height",
          "name": "height",
          "type": "INT",
          "widget": {
            "name": "height"
          },
          "link": 160
        },
        {
          "label": "upscale_method",
          "name": "upscale_method",
          "type": "COMBO",
          "widget": {
            "name": "upscale_method"
          }
        },
        {
          "label": "keep_proportion",
          "name": "keep_proportion",
          "type": "COMBO",
          "widget": {
            "name": "keep_proportion"
          }
        },
        {
          "label": "pad_color",
          "name": "pad_color",
          "type": "STRING",
          "widget": {
            "name": "pad_color"
          }
        },
        {
          "label": "crop_position",
          "name": "crop_position",
          "type": "COMBO",
          "widget": {
            "name": "crop_position"
          }
        },
        {
          "label": "divisible_by",
          "name": "divisible_by",
          "type": "INT",
          "widget": {
            "name": "divisible_by"
          }
        },
        {
          "label": "device",
          "name": "device",
          "shape": 7,
          "type": "COMBO",
          "widget": {
            "name": "device"
          }
        }
      ],
      "outputs": [
        {
          "label": "IMAGE",
          "name": "IMAGE",
          "type": "IMAGE",
          "links": [
            199
          ]
        },
        {
          "label": "width",
          "name": "width",
          "type": "INT",
          "links": [
            205
          ]
        },
        {
          "label": "height",
          "name": "height",
          "type": "INT",
          "links": [
            206
          ]
        },
        {
          "label": "mask",
          "name": "mask",
          "type": "MASK"
        }
      ],
      "properties": {
        "Node name for S&R": "ImageResizeKJv2",
        "cnr_id": "comfyui-kjnodes",
        "ver": "5dcda71011870278c35d92ff77a677ed2e538f2d",
        "widget_ue_connectable": {
          "width": true,
          "height": true
        }
      },
      "widgets_values": [
        480,
        720,
        "lanczos",
        "crop",
        "0, 0, 0",
        "center",
        16,
        "cpu"
      ]
    },
    {
      "id": 160,
      "type": "GetNode",
      "pos": [
        642.8670043945312,
        -26.582597732543945
      ],
      "size": [
        283.8118591308594,
        59.17063522338867
      ],
      "flags": {},
      "order": 7,
      "mode": 0,
      "inputs": [],
      "outputs": [
        {
          "label": "WANVAE",
          "name": "WANVAE",
          "type": "WANVAE",
          "links": [
            198
          ]
        }
      ],
      "title": "Get_vae",
      "properties": {
        "widget_ue_connectable": {}
      },
      "widgets_values": [
        "vae"
      ]
    },
    {
      "id": 163,
      "type": "GetNode",
      "pos": [
        651.1788330078125,
        69.75983428955078
      ],
      "size": [
        266.09814453125,
        69.3497543334961
      ],
      "flags": {},
      "order": 8,
      "mode": 0,
      "inputs": [],
      "outputs": [
        {
          "label": "IMAGE",
          "name": "IMAGE",
          "type": "IMAGE",
          "links": [
            204
          ]
        }
      ],
      "title": "Get_controlvideo",
      "properties": {
        "widget_ue_connectable": {}
      },
      "widgets_values": [
        "controlvideo"
      ],
      "color": "#2a363b",
      "bgcolor": "#3f5159"
    },
    {
      "id": 1,
      "type": "WanVideoModelLoader",
      "pos": [
        2110.447021484375,
        -388.4396057128906
      ],
      "size": [
        386.96685791015625,
        338
      ],
      "flags": {},
      "order": 31,
      "mode": 0,
      "inputs": [
        {
          "label": "compile_args",
          "name": "compile_args",
          "shape": 7,
          "type": "WANCOMPILEARGS"
        },
        {
          "label": "block_swap_args",
          "name": "block_swap_args",
          "shape": 7,
          "type": "BLOCKSWAPARGS",
          "link": 74
        },
        {
          "label": "lora",
          "name": "lora",
          "shape": 7,
          "type": "WANVIDLORA",
          "link": 168
        },
        {
          "label": "vram_management_args",
          "name": "vram_management_args",
          "shape": 7,
          "type": "VRAM_MANAGEMENTARGS"
        },
        {
          "label": "extra_model",
          "name": "extra_model",
          "shape": 7,
          "type": "VACEPATH"
        },
        {
          "label": "fantasytalking_model",
          "name": "fantasytalking_model",
          "shape": 7,
          "type": "FANTASYTALKINGMODEL"
        },
        {
          "label": "multitalk_model",
          "name": "multitalk_model",
          "shape": 7,
          "type": "MULTITALKMODEL"
        },
        {
          "label": "fantasyportrait_model",
          "name": "fantasyportrait_model",
          "shape": 7,
          "type": "FANTASYPORTRAITMODEL"
        },
        {
          "label": "model",
          "name": "model",
          "type": "COMBO",
          "widget": {
            "name": "model"
          }
        },
        {
          "label": "base_precision",
          "name": "base_precision",
          "type": "COMBO",
          "widget": {
            "name": "base_precision"
          }
        },
        {
          "label": "quantization",
          "name": "quantization",
          "type": "COMBO",
          "widget": {
            "name": "quantization"
          }
        },
        {
          "label": "load_device",
          "name": "load_device",
          "type": "COMBO",
          "widget": {
            "name": "load_device"
          }
        },
        {
          "label": "attention_mode",
          "name": "attention_mode",
          "shape": 7,
          "type": "COMBO",
          "widget": {
            "name": "attention_mode"
          }
        },
        {
          "label": "rms_norm_function",
          "name": "rms_norm_function",
          "shape": 7,
          "type": "COMBO",
          "widget": {
            "name": "rms_norm_function"
          }
        },
        {
          "label": "vace_model",
          "name": "vace_model",
          "shape": 7,
          "type": "VACEPATH"
        }
      ],
      "outputs": [
        {
          "label": "model",
          "name": "model",
          "type": "WANVIDEOMODEL",
          "slot_index": 0,
          "links": [
            2
          ]
        }
      ],
      "properties": {
        "Node name for S&R": "WanVideoModelLoader",
        "cnr_id": "ComfyUI-WanVideoWrapper",
        "ver": "d9b1f4d1a5aea91d101ae97a54714a5861af3f50",
        "widget_ue_connectable": {}
      },
      "widgets_values": [
        "Wan2_1-I2V-14B-480P_fp8_e4m3fn.safetensors",
        "fp16",
        "fp8_e4m3fn",
        "offload_device",
        "sageattn",
        "default"
      ],
      "color": "#223",
      "bgcolor": "#335"
    },
    {
      "id": 159,
      "type": "WanVideoImageToVideoEncode",
      "pos": [
        1340.659423828125,
        -395.3049621582031
      ],
      "size": [
        307.308349609375,
        409.42791748046875
      ],
      "flags": {},
      "order": 39,
      "mode": 0,
      "inputs": [
        {
          "label": "vae",
          "name": "vae",
          "shape": 7,
          "type": "WANVAE",
          "link": 198
        },
        {
          "label": "clip_embeds",
          "name": "clip_embeds",
          "shape": 7,
          "type": "WANVIDIMAGE_CLIPEMBEDS",
          "link": 208
        },
        {
          "label": "start_image",
          "name": "start_image",
          "shape": 7,
          "type": "IMAGE",
          "link": 199
        },
        {
          "label": "end_image",
          "name": "end_image",
          "shape": 7,
          "type": "IMAGE"
        },
        {
          "label": "control_embeds",
          "name": "control_embeds",
          "shape": 7,
          "type": "WANVIDIMAGE_EMBEDS"
        },
        {
          "label": "temporal_mask",
          "name": "temporal_mask",
          "shape": 7,
          "type": "MASK"
        },
        {
          "label": "extra_latents",
          "name": "extra_latents",
          "shape": 7,
          "type": "LATENT"
        },
        {
          "label": "add_cond_latents",
          "name": "add_cond_latents",
          "shape": 7,
          "type": "ADD_COND_LATENTS"
        },
        {
          "label": "width",
          "name": "width",
          "type": "INT",
          "widget": {
            "name": "width"
          },
          "link": 205
        },
        {
          "label": "height",
          "name": "height",
          "type": "INT",
          "widget": {
            "name": "height"
          },
          "link": 206
        },
        {
          "label": "num_frames",
          "name": "num_frames",
          "type": "INT",
          "widget": {
            "name": "num_frames"
          },
          "link": 203
        },
        {
          "label": "noise_aug_strength",
          "name": "noise_aug_strength",
          "type": "FLOAT",
          "widget": {
            "name": "noise_aug_strength"
          }
        },
        {
          "label": "start_latent_strength",
          "name": "start_latent_strength",
          "type": "FLOAT",
          "widget": {
            "name": "start_latent_strength"
          }
        },
        {
          "label": "end_latent_strength",
          "name": "end_latent_strength",
          "type": "FLOAT",
          "widget": {
            "name": "end_latent_strength"
          }
        },
        {
          "label": "force_offload",
          "name": "force_offload",
          "type": "BOOLEAN",
          "widget": {
            "name": "force_offload"
          }
        },
        {
          "label": "fun_or_fl2v_model",
          "name": "fun_or_fl2v_model",
          "shape": 7,
          "type": "BOOLEAN",
          "widget": {
            "name": "fun_or_fl2v_model"
          }
        },
        {
          "label": "tiled_vae",
          "name": "tiled_vae",
          "shape": 7,
          "type": "BOOLEAN",
          "widget": {
            "name": "tiled_vae"
          }
        }
      ],
      "outputs": [
        {
          "label": "image_embeds",
          "name": "image_embeds",
          "type": "WANVIDIMAGE_EMBEDS",
          "links": [
            200
          ]
        }
      ],
      "properties": {
        "Node name for S&R": "WanVideoImageToVideoEncode",
        "widget_ue_connectable": {}
      },
      "widgets_values": [
        832,
        480,
        81,
        0,
        1,
        1,
        true,
        true,
        false
      ]
    },
    {
      "id": 161,
      "type": "SetNode",
      "pos": [
        1334.794921875,
        62.30483627319336
      ],
      "size": [
        308.5263671875,
        58
      ],
      "flags": {},
      "order": 43,
      "mode": 0,
      "inputs": [
        {
          "label": "WANVIDIMAGE_EMBEDS",
          "name": "WANVIDIMAGE_EMBEDS",
          "type": "WANVIDIMAGE_EMBEDS",
          "link": 200
        }
      ],
      "outputs": [
        {
          "label": "*",
          "name": "*",
          "type": "*"
        }
      ],
      "title": "Set_image_embeds",
      "properties": {
        "previousName": "image_embeds",
        "widget_ue_connectable": {}
      },
      "widgets_values": [
        "image_embeds"
      ]
    },
    {
      "id": 156,
      "type": "GetImageSizeAndCount",
      "pos": [
        645.9107666015625,
        185.78993225097656
      ],
      "size": [
        277.20001220703125,
        86
      ],
      "flags": {},
      "order": 26,
      "mode": 0,
      "inputs": [
        {
          "label": "image",
          "name": "image",
          "type": "IMAGE",
          "link": 204
        }
      ],
      "outputs": [
        {
          "label": "image",
          "name": "image",
          "type": "IMAGE",
          "links": [
            207
          ]
        },
        {
          "label": "width",
          "name": "width",
          "type": "INT"
        },
        {
          "label": "height",
          "name": "height",
          "type": "INT"
        },
        {
          "label": "count",
          "name": "count",
          "type": "INT",
          "links": [
            203
          ]
        }
      ],
      "properties": {
        "Node name for S&R": "GetImageSizeAndCount",
        "widget_ue_connectable": {}
      },
      "widgets_values": []
    },
    {
      "id": 169,
      "type": "WanVideoClipVisionEncode",
      "pos": [
        991.2837524414062,
        -60.72321701049805
      ],
      "size": [
        300.5798034667969,
        262
      ],
      "flags": {},
      "order": 36,
      "mode": 0,
      "inputs": [
        {
          "label": "clip_vision",
          "name": "clip_vision",
          "type": "CLIP_VISION",
          "link": 209
        },
        {
          "label": "image_1",
          "name": "image_1",
          "type": "IMAGE",
          "link": 207
        },
        {
          "label": "image_2",
          "name": "image_2",
          "shape": 7,
          "type": "IMAGE"
        },
        {
          "label": "negative_image",
          "name": "negative_image",
          "shape": 7,
          "type": "IMAGE"
        },
        {
          "label": "strength_1",
          "name": "strength_1",
          "type": "FLOAT",
          "widget": {
            "name": "strength_1"
          }
        },
        {
          "label": "strength_2",
          "name": "strength_2",
          "type": "FLOAT",
          "widget": {
            "name": "strength_2"
          }
        },
        {
          "label": "crop",
          "name": "crop",
          "type": "COMBO",
          "widget": {
            "name": "crop"
          }
        },
        {
          "label": "combine_embeds",
          "name": "combine_embeds",
          "type": "COMBO",
          "widget": {
            "name": "combine_embeds"
          }
        },
        {
          "label": "force_offload",
          "name": "force_offload",
          "type": "BOOLEAN",
          "widget": {
            "name": "force_offload"
          }
        },
        {
          "label": "tiles",
          "name": "tiles",
          "shape": 7,
          "type": "INT",
          "widget": {
            "name": "tiles"
          }
        },
        {
          "label": "ratio",
          "name": "ratio",
          "shape": 7,
          "type": "FLOAT",
          "widget": {
            "name": "ratio"
          }
        }
      ],
      "outputs": [
        {
          "label": "image_embeds",
          "name": "image_embeds",
          "type": "WANVIDIMAGE_CLIPEMBEDS",
          "links": [
            208
          ]
        }
      ],
      "properties": {
        "Node name for S&R": "WanVideoClipVisionEncode",
        "widget_ue_connectable": {}
      },
      "widgets_values": [
        1,
        1,
        "center",
        "average",
        true,
        0,
        0.5
      ]
    },
    {
      "id": 167,
      "type": "CLIPVisionLoader",
      "pos": [
        633.2879638671875,
        322.40191650390625
      ],
      "size": [
        315,
        58
      ],
      "flags": {},
      "order": 9,
      "mode": 0,
      "inputs": [
        {
          "label": "clip_name",
          "name": "clip_name",
          "type": "COMBO",
          "widget": {
            "name": "clip_name"
          }
        }
      ],
      "outputs": [
        {
          "label": "CLIP_VISION",
          "name": "CLIP_VISION",
          "type": "CLIP_VISION",
          "links": [
            209
          ]
        }
      ],
      "properties": {
        "Node name for S&R": "CLIPVisionLoader",
        "widget_ue_connectable": {}
      },
      "widgets_values": [
        "clip_vision_h.safetensors"
      ]
    },
    {
      "id": 30,
      "type": "VHS_VideoCombine",
      "pos": [
        3338.578369140625,
        -455.5120544433594
      ],
      "size": [
        411.2537536621094,
        1062.44775390625
      ],
      "flags": {},
      "order": 45,
      "mode": 0,
      "inputs": [
        {
          "label": "images",
          "name": "images",
          "type": "IMAGE",
          "link": 29
        },
        {
          "label": "audio",
          "name": "audio",
          "shape": 7,
          "type": "AUDIO"
        },
        {
          "label": "meta_batch",
          "name": "meta_batch",
          "shape": 7,
          "type": "VHS_BatchManager"
        },
        {
          "label": "vae",
          "name": "vae",
          "shape": 7,
          "type": "VAE"
        },
        {
          "label": "frame_rate",
          "name": "frame_rate",
          "type": "FLOAT",
          "widget": {
            "name": "frame_rate"
          }
        },
        {
          "label": "loop_count",
          "name": "loop_count",
          "type": "INT",
          "widget": {
            "name": "loop_count"
          }
        },
        {
          "label": "filename_prefix",
          "name": "filename_prefix",
          "type": "STRING",
          "widget": {
            "name": "filename_prefix"
          }
        },
        {
          "label": "format",
          "name": "format",
          "type": "COMBO",
          "widget": {
            "name": "format"
          }
        },
        {
          "label": "pingpong",
          "name": "pingpong",
          "type": "BOOLEAN",
          "widget": {
            "name": "pingpong"
          }
        },
        {
          "label": "save_output",
          "name": "save_output",
          "type": "BOOLEAN",
          "widget": {
            "name": "save_output"
          }
        },
        {
          "label": "no_preview",
          "name": "no_preview",
          "shape": 7,
          "type": "BOOLEAN",
          "widget": {
            "name": "no_preview"
          }
        }
      ],
      "outputs": [
        {
          "label": "Filenames",
          "name": "Filenames",
          "type": "VHS_FILENAMES"
        }
      ],
      "properties": {
        "Node name for S&R": "VHS_VideoCombine",
        "cnr_id": "comfyui-videohelpersuite",
        "ver": "0a75c7958fe320efcb052f1d9f8451fd20c730a8",
        "widget_ue_connectable": {}
      },
      "widgets_values": {
        "frame_rate": 16,
        "loop_count": 0,
        "filename_prefix": "AnimateDiff",
        "format": "video/h264-mp4",
        "pix_fmt": "yuv420p",
        "crf": 19,
        "save_metadata": true,
        "trim_to_audio": false,
        "pingpong": false,
        "save_output": true,
        "no_preview": false,
        "videopreview": {
          "paused": false,
          "hidden": false,
          "params": {
            "score": "0",
            "filename": "AnimateDiff_00001_p86_efqpa_1763620647.mp4",
            "workflow": "AnimateDiff_00001_p86.png",
            "fullpath": "/data/ComfyUI/personal/445aa9a89d7fa5567450f91c998092da/output/AnimateDiff_00001_p86.mp4",
            "format": "video/h264-mp4",
            "subfolder": "",
            "label": "Normal",
            "type": "output",
            "frame_rate": 16
          }
        }
      }
    },
    {
      "id": 153,
      "type": "SetNode",
      "pos": [
        2565.573486328125,
        7.251935005187988
      ],
      "size": [
        312.0850830078125,
        58
      ],
      "flags": {},
      "order": 33,
      "mode": 0,
      "inputs": [
        {
          "label": "WANVAE",
          "name": "WANVAE",
          "type": "WANVAE",
          "link": 186
        }
      ],
      "outputs": [
        {
          "label": "*",
          "name": "*",
          "type": "*"
        }
      ],
      "title": "Set_vae",
      "properties": {
        "previousName": "vae",
        "widget_ue_connectable": {}
      },
      "widgets_values": [
        "vae"
      ]
    },
    {
      "id": 117,
      "type": "Label (rgthree)",
      "pos": [
        1314.078125,
        -1299.660400390625
      ],
      "size": [
        666.10546875,
        36
      ],
      "flags": {
        "allow_interaction": true
      },
      "order": 10,
      "mode": 0,
      "inputs": [],
      "outputs": [],
      "title": "有趣的80后程序员：uni3c虚拟相机工作流",
      "properties": {
        "fontSize": 36,
        "fontFamily": "Arial",
        "fontColor": "#ffffff",
        "textAlign": "left",
        "backgroundColor": "transparent",
        "padding": 0,
        "borderRadius": 0,
        "widget_ue_connectable": {}
      },
      "color": "#fff0",
      "bgcolor": "#fff0"
    },
    {
      "id": 106,
      "type": "LoadImage",
      "pos": [
        625.33447265625,
        -391.7281188964844
      ],
      "size": [
        315,
        314
      ],
      "flags": {},
      "order": 11,
      "mode": 0,
      "inputs": [
        {
          "label": "image",
          "name": "image",
          "type": "COMBO",
          "widget": {
            "name": "image"
          }
        },
        {
          "label": "upload",
          "name": "upload",
          "type": "IMAGEUPLOAD",
          "widget": {
            "name": "upload"
          }
        }
      ],
      "outputs": [
        {
          "label": "IMAGE",
          "name": "IMAGE",
          "type": "IMAGE",
          "links": [
            138
          ]
        },
        {
          "label": "MASK",
          "name": "MASK",
          "type": "MASK"
        }
      ],
      "properties": {
        "Node name for S&R": "LoadImage",
        "cnr_id": "comfy-core",
        "ver": "0.3.41",
        "widget_ue_connectable": {}
      },
      "widgets_values": [
        "4d09621944f36a83799ace0acd7eea86fdb5da1157c4d914980d45a29a4e5d2e.png",
        "image"
      ]
    },
    {
      "id": 4,
      "type": "WanVideoSampler",
      "pos": [
        2930.171875,
        -161.43185424804688
      ],
      "size": [
        303.04217529296875,
        690
      ],
      "flags": {},
      "order": 42,
      "mode": 0,
      "inputs": [
        {
          "label": "model",
          "name": "model",
          "type": "WANVIDEOMODEL",
          "link": 2
        },
        {
          "label": "image_embeds",
          "name": "image_embeds",
          "type": "WANVIDIMAGE_EMBEDS",
          "link": 201
        },
        {
          "label": "text_embeds",
          "name": "text_embeds",
          "shape": 7,
          "type": "WANVIDEOTEXTEMBEDS",
          "link": 169
        },
        {
          "label": "samples",
          "name": "samples",
          "shape": 7,
          "type": "LATENT"
        },
        {
          "label": "feta_args",
          "name": "feta_args",
          "shape": 7,
          "type": "FETAARGS"
        },
        {
          "label": "context_options",
          "name": "context_options",
          "shape": 7,
          "type": "WANVIDCONTEXT"
        },
        {
          "label": "cache_args",
          "name": "cache_args",
          "shape": 7,
          "type": "CACHEARGS"
        },
        {
          "label": "flowedit_args",
          "name": "flowedit_args",
          "shape": 7,
          "type": "FLOWEDITARGS"
        },
        {
          "label": "slg_args",
          "name": "slg_args",
          "shape": 7,
          "type": "SLGARGS"
        },
        {
          "label": "loop_args",
          "name": "loop_args",
          "shape": 7,
          "type": "LOOPARGS"
        },
        {
          "label": "experimental_args",
          "name": "experimental_args",
          "shape": 7,
          "type": "EXPERIMENTALARGS"
        },
        {
          "label": "sigmas",
          "name": "sigmas",
          "shape": 7,
          "type": "SIGMAS"
        },
        {
          "label": "unianimate_poses",
          "name": "unianimate_poses",
          "shape": 7,
          "type": "UNIANIMATE_POSE"
        },
        {
          "label": "fantasytalking_embeds",
          "name": "fantasytalking_embeds",
          "shape": 7,
          "type": "FANTASYTALKING_EMBEDS"
        },
        {
          "label": "uni3c_embeds",
          "name": "uni3c_embeds",
          "shape": 7,
          "type": "UNI3C_EMBEDS",
          "link": 190
        },
        {
          "label": "multitalk_embeds",
          "name": "multitalk_embeds",
          "shape": 7,
          "type": "MULTITALK_EMBEDS"
        },
        {
          "label": "freeinit_args",
          "name": "freeinit_args",
          "shape": 7,
          "type": "FREEINITARGS"
        },
        {
          "label": "steps",
          "name": "steps",
          "type": "INT",
          "widget": {
            "name": "steps"
          }
        },
        {
          "label": "cfg",
          "name": "cfg",
          "type": "FLOAT",
          "widget": {
            "name": "cfg"
          }
        },
        {
          "label": "shift",
          "name": "shift",
          "type": "FLOAT",
          "widget": {
            "name": "shift"
          }
        },
        {
          "label": "seed",
          "name": "seed",
          "type": "INT",
          "widget": {
            "name": "seed"
          }
        },
        {
          "label": "force_offload",
          "name": "force_offload",
          "type": "BOOLEAN",
          "widget": {
            "name": "force_offload"
          }
        },
        {
          "label": "scheduler",
          "name": "scheduler",
          "type": "COMBO",
          "widget": {
            "name": "scheduler"
          }
        },
        {
          "label": "riflex_freq_index",
          "name": "riflex_freq_index",
          "type": "INT",
          "widget": {
            "name": "riflex_freq_index"
          }
        },
        {
          "label": "denoise_strength",
          "name": "denoise_strength",
          "shape": 7,
          "type": "FLOAT",
          "widget": {
            "name": "denoise_strength"
          }
        },
        {
          "label": "batched_cfg",
          "name": "batched_cfg",
          "shape": 7,
          "type": "BOOLEAN",
          "widget": {
            "name": "batched_cfg"
          }
        },
        {
          "label": "rope_function",
          "name": "rope_function",
          "shape": 7,
          "type": "COMBO",
          "widget": {
            "name": "rope_function"
          }
        },
        {
          "label": "start_step",
          "name": "start_step",
          "shape": 7,
          "type": "INT",
          "widget": {
            "name": "start_step"
          }
        },
        {
          "label": "end_step",
          "name": "end_step",
          "shape": 7,
          "type": "INT",
          "widget": {
            "name": "end_step"
          }
        },
        {
          "label": "add_noise_to_samples",
          "name": "add_noise_to_samples",
          "shape": 7,
          "type": "BOOLEAN",
          "widget": {
            "name": "add_noise_to_samples"
          }
        }
      ],
      "outputs": [
        {
          "label": "samples",
          "name": "samples",
          "type": "LATENT",
          "slot_index": 0,
          "links": [
            27
          ]
        },
        {
          "label": "denoised_samples",
          "name": "denoised_samples",
          "type": "LATENT"
        }
      ],
      "properties": {
        "Node name for S&R": "WanVideoSampler",
        "cnr_id": "ComfyUI-WanVideoWrapper",
        "ver": "d9b1f4d1a5aea91d101ae97a54714a5861af3f50",
        "widget_ue_connectable": {}
      },
      "widgets_values": [
        8,
        1.0000000000000002,
        5.000000000000001,
        398762215507914,
        "randomize",
        true,
        "unipc",
        0,
        1,
        "",
        "comfy",
        0,
        -1,
        false
      ]
    },
    {
      "id": 112,
      "type": "INTConstant",
      "pos": [
        29.97373390197754,
        -386.7318115234375
      ],
      "size": [
        210,
        58
      ],
      "flags": {},
      "order": 12,
      "mode": 0,
      "inputs": [
        {
          "label": "value",
          "name": "value",
          "type": "INT",
          "widget": {
            "name": "value"
          }
        }
      ],
      "outputs": [
        {
          "label": "value",
          "name": "value",
          "type": "INT",
          "links": [
            159,
            177
          ]
        }
      ],
      "properties": {
        "Node name for S&R": "INTConstant",
        "cnr_id": "comfyui-kjnodes",
        "ver": "52c2e31a903fec2dd654fb614ea82ba2757d5028",
        "widget_ue_connectable": {}
      },
      "widgets_values": [
        544
      ],
      "color": "#1b4669",
      "bgcolor": "#29699c"
    },
    {
      "id": 113,
      "type": "INTConstant",
      "pos": [
        26.026653289794922,
        -251.63046264648438
      ],
      "size": [
        210,
        58
      ],
      "flags": {},
      "order": 13,
      "mode": 0,
      "inputs": [
        {
          "label": "value",
          "name": "value",
          "type": "INT",
          "widget": {
            "name": "value"
          }
        }
      ],
      "outputs": [
        {
          "label": "value",
          "name": "value",
          "type": "INT",
          "links": [
            160,
            178
          ]
        }
      ],
      "properties": {
        "Node name for S&R": "INTConstant",
        "cnr_id": "comfyui-kjnodes",
        "ver": "52c2e31a903fec2dd654fb614ea82ba2757d5028",
        "widget_ue_connectable": {}
      },
      "widgets_values": [
        960
      ],
      "color": "#1b4669",
      "bgcolor": "#29699c"
    },
    {
      "id": 114,
      "type": "INTConstant",
      "pos": [
        25.873210906982422,
        -111.06831359863281
      ],
      "size": [
        210,
        58
      ],
      "flags": {},
      "order": 14,
      "mode": 0,
      "inputs": [
        {
          "label": "value",
          "name": "value",
          "type": "INT",
          "widget": {
            "name": "value"
          }
        }
      ],
      "outputs": [
        {
          "label": "value",
          "name": "value",
          "type": "INT",
          "links": [
            179
          ]
        }
      ],
      "properties": {
        "Node name for S&R": "INTConstant",
        "cnr_id": "comfyui-kjnodes",
        "ver": "52c2e31a903fec2dd654fb614ea82ba2757d5028",
        "widget_ue_connectable": {}
      },
      "widgets_values": [
        81
      ],
      "color": "#1b4669",
      "bgcolor": "#29699c"
    },
    {
      "id": 51,
      "type": "WanVideoBlockSwap",
      "pos": [
        1751.453857421875,
        -380.4378356933594
      ],
      "size": [
        315,
        202
      ],
      "flags": {},
      "order": 15,
      "mode": 0,
      "inputs": [
        {
          "label": "blocks_to_swap",
          "name": "blocks_to_swap",
          "type": "INT",
          "widget": {
            "name": "blocks_to_swap"
          }
        },
        {
          "label": "offload_img_emb",
          "name": "offload_img_emb",
          "type": "BOOLEAN",
          "widget": {
            "name": "offload_img_emb"
          }
        },
        {
          "label": "offload_txt_emb",
          "name": "offload_txt_emb",
          "type": "BOOLEAN",
          "widget": {
            "name": "offload_txt_emb"
          }
        },
        {
          "label": "use_non_blocking",
          "name": "use_non_blocking",
          "shape": 7,
          "type": "BOOLEAN",
          "widget": {
            "name": "use_non_blocking"
          }
        },
        {
          "label": "vace_blocks_to_swap",
          "name": "vace_blocks_to_swap",
          "shape": 7,
          "type": "INT",
          "widget": {
            "name": "vace_blocks_to_swap"
          }
        },
        {
          "label": "prefetch_blocks",
          "name": "prefetch_blocks",
          "shape": 7,
          "type": "INT",
          "widget": {
            "name": "prefetch_blocks"
          }
        },
        {
          "label": "block_swap_debug",
          "name": "block_swap_debug",
          "shape": 7,
          "type": "BOOLEAN",
          "widget": {
            "name": "block_swap_debug"
          }
        }
      ],
      "outputs": [
        {
          "label": "block_swap_args",
          "name": "block_swap_args",
          "type": "BLOCKSWAPARGS",
          "slot_index": 0,
          "links": [
            74
          ]
        }
      ],
      "properties": {
        "Node name for S&R": "WanVideoBlockSwap",
        "cnr_id": "ComfyUI-WanVideoWrapper",
        "ver": "3869b0482b615b6a8fd6f346467c5ef6627eed72",
        "widget_ue_connectable": {}
      },
      "widgets_values": [
        30,
        false,
        false,
        true,
        15,
        0,
        false
      ],
      "color": "#223",
      "bgcolor": "#335"
    },
    {
      "id": 130,
      "type": "WanVideoLoraSelect",
      "pos": [
        1747.4521484375,
        -123.95521545410156
      ],
      "size": [
        332.459228515625,
        157.95094299316406
      ],
      "flags": {},
      "order": 16,
      "mode": 0,
      "inputs": [
        {
          "label": "prev_lora",
          "name": "prev_lora",
          "shape": 7,
          "type": "WANVIDLORA"
        },
        {
          "label": "blocks",
          "name": "blocks",
          "shape": 7,
          "type": "SELECTEDBLOCKS"
        },
        {
          "label": "lora",
          "name": "lora",
          "type": "COMBO",
          "widget": {
            "name": "lora"
          }
        },
        {
          "label": "strength",
          "name": "strength",
          "type": "FLOAT",
          "widget": {
            "name": "strength"
          }
        },
        {
          "label": "low_mem_load",
          "name": "low_mem_load",
          "shape": 7,
          "type": "BOOLEAN",
          "widget": {
            "name": "low_mem_load"
          }
        },
        {
          "label": "merge_loras",
          "name": "merge_loras",
          "shape": 7,
          "type": "BOOLEAN",
          "widget": {
            "name": "merge_loras"
          }
        }
      ],
      "outputs": [
        {
          "label": "lora",
          "name": "lora",
          "type": "WANVIDLORA",
          "links": [
            168
          ]
        }
      ],
      "properties": {
        "Node name for S&R": "WanVideoLoraSelect",
        "cnr_id": "ComfyUI-WanVideoWrapper",
        "ver": "8479624614ec0d52e982bbbab633736fb1a15eef",
        "widget_ue_connectable": {}
      },
      "widgets_values": [
        "lightx2v_I2V_14B_480p_cfg_step_distill_rank64_bf16.safetensors",
        1.0000000000000002,
        false,
        true
      ]
    },
    {
      "id": 2,
      "type": "LoadWanVideoT5TextEncoder",
      "pos": [
        2122.372314453125,
        1.535149097442627
      ],
      "size": [
        377.1661376953125,
        130
      ],
      "flags": {},
      "order": 17,
      "mode": 0,
      "inputs": [
        {
          "label": "model_name",
          "name": "model_name",
          "type": "COMBO",
          "widget": {
            "name": "model_name"
          }
        },
        {
          "label": "precision",
          "name": "precision",
          "type": "COMBO",
          "widget": {
            "name": "precision"
          }
        },
        {
          "label": "load_device",
          "name": "load_device",
          "shape": 7,
          "type": "COMBO",
          "widget": {
            "name": "load_device"
          }
        },
        {
          "label": "quantization",
          "name": "quantization",
          "shape": 7,
          "type": "COMBO",
          "widget": {
            "name": "quantization"
          }
        }
      ],
      "outputs": [
        {
          "label": "wan_t5_model",
          "name": "wan_t5_model",
          "type": "WANTEXTENCODER",
          "slot_index": 0,
          "links": [
            3
          ]
        }
      ],
      "properties": {
        "Node name for S&R": "LoadWanVideoT5TextEncoder",
        "cnr_id": "ComfyUI-WanVideoWrapper",
        "ver": "d9b1f4d1a5aea91d101ae97a54714a5861af3f50",
        "widget_ue_connectable": {}
      },
      "widgets_values": [
        "umt5-xxl-enc-bf16.safetensors",
        "bf16",
        "offload_device",
        "disabled"
      ],
      "color": "#332922",
      "bgcolor": "#593930"
    },
    {
      "id": 3,
      "type": "WanVideoVAELoader",
      "pos": [
        2126.374755859375,
        194.79307556152344
      ],
      "size": [
        372.7727966308594,
        82
      ],
      "flags": {},
      "order": 18,
      "mode": 0,
      "inputs": [
        {
          "label": "compile_args",
          "name": "compile_args",
          "shape": 7,
          "type": "WANCOMPILEARGS"
        },
        {
          "label": "model_name",
          "name": "model_name",
          "type": "COMBO",
          "widget": {
            "name": "model_name"
          }
        },
        {
          "label": "precision",
          "name": "precision",
          "shape": 7,
          "type": "COMBO",
          "widget": {
            "name": "precision"
          }
        }
      ],
      "outputs": [
        {
          "label": "vae",
          "name": "vae",
          "type": "WANVAE",
          "slot_index": 0,
          "links": [
            28,
            186
          ]
        }
      ],
      "properties": {
        "Node name for S&R": "WanVideoVAELoader",
        "cnr_id": "ComfyUI-WanVideoWrapper",
        "ver": "d9b1f4d1a5aea91d101ae97a54714a5861af3f50",
        "widget_ue_connectable": {}
      },
      "widgets_values": [
        "Wan2_1_VAE_bf16.safetensors",
        "bf16"
      ],
      "color": "#322",
      "bgcolor": "#533"
    },
    {
      "id": 6,
      "type": "WanVideoTextEncode",
      "pos": [
        2540.8212890625,
        -404.6528015136719
      ],
      "size": [
        334.9443664550781,
        234
      ],
      "flags": {},
      "order": 32,
      "mode": 0,
      "inputs": [
        {
          "label": "t5",
          "name": "t5",
          "shape": 7,
          "type": "WANTEXTENCODER",
          "link": 3
        },
        {
          "label": "model_to_offload",
          "name": "model_to_offload",
          "shape": 7,
          "type": "WANVIDEOMODEL"
        },
        {
          "label": "positive_prompt",
          "name": "positive_prompt",
          "type": "STRING",
          "widget": {
            "name": "positive_prompt"
          }
        },
        {
          "label": "negative_prompt",
          "name": "negative_prompt",
          "type": "STRING",
          "widget": {
            "name": "negative_prompt"
          }
        },
        {
          "label": "force_offload",
          "name": "force_offload",
          "shape": 7,
          "type": "BOOLEAN",
          "widget": {
            "name": "force_offload"
          }
        },
        {
          "label": "use_disk_cache",
          "name": "use_disk_cache",
          "shape": 7,
          "type": "BOOLEAN",
          "widget": {
            "name": "use_disk_cache"
          }
        },
        {
          "label": "device",
          "name": "device",
          "shape": 7,
          "type": "COMBO",
          "widget": {
            "name": "device"
          }
        }
      ],
      "outputs": [
        {
          "label": "text_embeds",
          "name": "text_embeds",
          "type": "WANVIDEOTEXTEMBEDS",
          "links": [
            169
          ]
        }
      ],
      "properties": {
        "Node name for S&R": "WanVideoTextEncode",
        "cnr_id": "ComfyUI-WanVideoWrapper",
        "ver": "ce6522c2279c30ed6ac157cbfacd8e15cb1cfae2",
        "widget_ue_connectable": {}
      },
      "widgets_values": [
        "best quality,dynamic motion",
        "色调艳丽，过曝，静态，细节模糊不清，字幕，风格，作品，画作，画面，静止，整体发灰，最差质量，低质量，JPEG压缩残留，丑陋的，残缺的，多余的手指，画得不好的手部，画得不好的脸部，畸形的，毁容的，形态畸形的肢体，手指融合，静止不动的画面，杂乱的背景，三条腿，背景人很多，倒着走",
        true,
        false,
        "gpu"
      ]
    },
    {
      "id": 162,
      "type": "GetNode",
      "pos": [
        2549.6904296875,
        -112.74060821533203
      ],
      "size": [
        329.2170104980469,
        78.76557922363281
      ],
      "flags": {},
      "order": 19,
      "mode": 0,
      "inputs": [],
      "outputs": [
        {
          "label": "WANVIDIMAGE_EMBEDS",
          "name": "WANVIDIMAGE_EMBEDS",
          "type": "WANVIDIMAGE_EMBEDS",
          "links": [
            201
          ]
        }
      ],
      "title": "Get_image_embeds",
      "properties": {
        "widget_ue_connectable": {}
      },
      "widgets_values": [
        "image_embeds"
      ]
    },
    {
      "id": 147,
      "type": "GetNode",
      "pos": [
        627.9607543945312,
        733.1566772460938
      ],
      "size": [
        210,
        58
      ],
      "flags": {},
      "order": 20,
      "mode": 0,
      "inputs": [],
      "outputs": [
        {
          "label": "INT",
          "name": "INT",
          "type": "INT",
          "links": [
            181
          ]
        }
      ],
      "title": "Get_widht",
      "properties": {
        "widget_ue_connectable": {}
      },
      "widgets_values": [
        "widht"
      ],
      "color": "#1b4669",
      "bgcolor": "#29699c"
    },
    {
      "id": 148,
      "type": "GetNode",
      "pos": [
        627.92236328125,
        856.2158203125
      ],
      "size": [
        210,
        58
      ],
      "flags": {},
      "order": 21,
      "mode": 0,
      "inputs": [],
      "outputs": [
        {
          "label": "INT",
          "name": "INT",
          "type": "INT",
          "links": [
            182
          ]
        }
      ],
      "title": "Get_height",
      "properties": {
        "widget_ue_connectable": {}
      },
      "widgets_values": [
        "height"
      ],
      "color": "#1b4669",
      "bgcolor": "#29699c"
    },
    {
      "id": 144,
      "type": "GetNode",
      "pos": [
        636.6341552734375,
        623.7171630859375
      ],
      "size": [
        210,
        60
      ],
      "flags": {},
      "order": 22,
      "mode": 0,
      "inputs": [],
      "outputs": [
        {
          "label": "INT",
          "name": "INT",
          "type": "INT",
          "links": [
            180
          ]
        }
      ],
      "title": "Get_frames",
      "properties": {
        "widget_ue_connectable": {}
      },
      "widgets_values": [
        "frames"
      ],
      "color": "#1b4669",
      "bgcolor": "#29699c"
    },
    {
      "id": 146,
      "type": "ImageResizeKJv2",
      "pos": [
        1139.228515625,
        603.8819580078125
      ],
      "size": [
        315,
        336
      ],
      "flags": {},
      "order": 37,
      "mode": 0,
      "inputs": [
        {
          "label": "image",
          "name": "image",
          "type": "IMAGE",
          "link": 183
        },
        {
          "label": "mask",
          "name": "mask",
          "shape": 7,
          "type": "MASK"
        },
        {
          "label": "width",
          "name": "width",
          "type": "INT",
          "widget": {
            "name": "width"
          },
          "link": 181
        },
        {
          "label": "height",
          "name": "height",
          "type": "INT",
          "widget": {
            "name": "height"
          },
          "link": 182
        },
        {
          "label": "upscale_method",
          "name": "upscale_method",
          "type": "COMBO",
          "widget": {
            "name": "upscale_method"
          }
        },
        {
          "label": "keep_proportion",
          "name": "keep_proportion",
          "type": "COMBO",
          "widget": {
            "name": "keep_proportion"
          }
        },
        {
          "label": "pad_color",
          "name": "pad_color",
          "type": "STRING",
          "widget": {
            "name": "pad_color"
          }
        },
        {
          "label": "crop_position",
          "name": "crop_position",
          "type": "COMBO",
          "widget": {
            "name": "crop_position"
          }
        },
        {
          "label": "divisible_by",
          "name": "divisible_by",
          "type": "INT",
          "widget": {
            "name": "divisible_by"
          }
        },
        {
          "label": "device",
          "name": "device",
          "shape": 7,
          "type": "COMBO",
          "widget": {
            "name": "device"
          }
        }
      ],
      "outputs": [
        {
          "label": "IMAGE",
          "name": "IMAGE",
          "type": "IMAGE",
          "links": [
            184,
            185
          ]
        },
        {
          "label": "width",
          "name": "width",
          "type": "INT"
        },
        {
          "label": "height",
          "name": "height",
          "type": "INT"
        },
        {
          "label": "mask",
          "name": "mask",
          "type": "MASK"
        }
      ],
      "properties": {
        "Node name for S&R": "ImageResizeKJv2",
        "widget_ue_connectable": {}
      },
      "widgets_values": [
        512,
        512,
        "nearest-exact",
        "crop",
        "0, 0, 0",
        "center",
        16,
        "cpu"
      ]
    },
    {
      "id": 150,
      "type": "SetNode",
      "pos": [
        1167.715576171875,
        979.4137573242188
      ],
      "size": [
        210,
        60
      ],
      "flags": {},
      "order": 41,
      "mode": 0,
      "inputs": [
        {
          "label": "IMAGE",
          "name": "IMAGE",
          "type": "IMAGE",
          "link": 185
        }
      ],
      "outputs": [
        {
          "label": "*",
          "name": "*",
          "type": "*"
        }
      ],
      "title": "Set_controlvideo",
      "properties": {
        "previousName": "controlvideo",
        "widget_ue_connectable": {}
      },
      "widgets_values": [
        "controlvideo"
      ],
      "color": "#2a363b",
      "bgcolor": "#3f5159"
    },
    {
      "id": 152,
      "type": "GetNode",
      "pos": [
        1841.1806640625,
        847.4285278320312
      ],
      "size": [
        210,
        60
      ],
      "flags": {},
      "order": 23,
      "mode": 0,
      "inputs": [],
      "outputs": [
        {
          "label": "WANVAE",
          "name": "WANVAE",
          "type": "WANVAE",
          "links": [
            187
          ]
        }
      ],
      "title": "Get_vae",
      "properties": {
        "widget_ue_connectable": {}
      },
      "widgets_values": [
        "vae"
      ]
    },
    {
      "id": 154,
      "type": "GetNode",
      "pos": [
        1842.372314453125,
        940.856201171875
      ],
      "size": [
        210,
        58
      ],
      "flags": {},
      "order": 24,
      "mode": 0,
      "inputs": [],
      "outputs": [
        {
          "label": "IMAGE",
          "name": "IMAGE",
          "type": "IMAGE",
          "links": [
            188
          ]
        }
      ],
      "title": "Get_controlvideo",
      "properties": {
        "widget_ue_connectable": {}
      },
      "widgets_values": [
        "controlvideo"
      ],
      "color": "#2a363b",
      "bgcolor": "#3f5159"
    },
    {
      "id": 135,
      "type": "WanVideoUni3C_embeds",
      "pos": [
        2430.14013671875,
        626.556884765625
      ],
      "size": [
        330,
        146
      ],
      "flags": {},
      "order": 38,
      "mode": 0,
      "inputs": [
        {
          "label": "controlnet",
          "name": "controlnet",
          "type": "WANVIDEOCONTROLNET",
          "link": 175
        },
        {
          "label": "render_latent",
          "name": "render_latent",
          "shape": 7,
          "type": "LATENT",
          "link": 189
        },
        {
          "label": "render_mask",
          "name": "render_mask",
          "shape": 7,
          "type": "MASK"
        },
        {
          "label": "strength",
          "name": "strength",
          "type": "FLOAT",
          "widget": {
            "name": "strength"
          }
        },
        {
          "label": "start_percent",
          "name": "start_percent",
          "type": "FLOAT",
          "widget": {
            "name": "start_percent"
          }
        },
        {
          "label": "end_percent",
          "name": "end_percent",
          "type": "FLOAT",
          "widget": {
            "name": "end_percent"
          }
        }
      ],
      "outputs": [
        {
          "label": "uni3c_embeds",
          "name": "uni3c_embeds",
          "type": "UNI3C_EMBEDS",
          "links": [
            190
          ]
        }
      ],
      "properties": {
        "Node name for S&R": "WanVideoUni3C_embeds",
        "widget_ue_connectable": {}
      },
      "widgets_values": [
        1,
        0,
        1
      ]
    },
    {
      "id": 136,
      "type": "WanVideoUni3C_ControlnetLoader",
      "pos": [
        1811.14794921875,
        619.9063720703125
      ],
      "size": [
        566.053466796875,
        164.55526733398438
      ],
      "flags": {},
      "order": 25,
      "mode": 0,
      "inputs": [
        {
          "label": "compile_args",
          "name": "compile_args",
          "shape": 7,
          "type": "WANCOMPILEARGS"
        },
        {
          "label": "model",
          "name": "model",
          "type": "COMBO",
          "widget": {
            "name": "model"
          }
        },
        {
          "label": "base_precision",
          "name": "base_precision",
          "type": "COMBO",
          "widget": {
            "name": "base_precision"
          }
        },
        {
          "label": "quantization",
          "name": "quantization",
          "type": "COMBO",
          "widget": {
            "name": "quantization"
          }
        },
        {
          "label": "load_device",
          "name": "load_device",
          "type": "COMBO",
          "widget": {
            "name": "load_device"
          }
        },
        {
          "label": "attention_mode",
          "name": "attention_mode",
          "type": "COMBO",
          "widget": {
            "name": "attention_mode"
          }
        }
      ],
      "outputs": [
        {
          "label": "controlnet",
          "name": "controlnet",
          "type": "WANVIDEOCONTROLNET",
          "links": [
            175
          ]
        }
      ],
      "properties": {
        "Node name for S&R": "WanVideoUni3C_ControlnetLoader",
        "widget_ue_connectable": {}
      },
      "widgets_values": [
        "Wan21_Uni3C_controlnet_fp16.safetensors",
        "fp16",
        "disabled",
        "main_device",
        "sageattn"
      ]
    },
    {
      "id": 151,
      "type": "WanVideoEncode",
      "pos": [
        2060.83642578125,
        844.2047729492188
      ],
      "size": [
        315,
        242
      ],
      "flags": {},
      "order": 35,
      "mode": 0,
      "inputs": [
        {
          "label": "vae",
          "name": "vae",
          "type": "WANVAE",
          "link": 187
        },
        {
          "label": "image",
          "name": "image",
          "type": "IMAGE",
          "link": 188
        },
        {
          "label": "mask",
          "name": "mask",
          "shape": 7,
          "type": "MASK"
        },
        {
          "label": "enable_vae_tiling",
          "name": "enable_vae_tiling",
          "type": "BOOLEAN",
          "widget": {
            "name": "enable_vae_tiling"
          }
        },
        {
          "label": "tile_x",
          "name": "tile_x",
          "type": "INT",
          "widget": {
            "name": "tile_x"
          }
        },
        {
          "label": "tile_y",
          "name": "tile_y",
          "type": "INT",
          "widget": {
            "name": "tile_y"
          }
        },
        {
          "label": "tile_stride_x",
          "name": "tile_stride_x",
          "type": "INT",
          "widget": {
            "name": "tile_stride_x"
          }
        },
        {
          "label": "tile_stride_y",
          "name": "tile_stride_y",
          "type": "INT",
          "widget": {
            "name": "tile_stride_y"
          }
        },
        {
          "label": "noise_aug_strength",
          "name": "noise_aug_strength",
          "shape": 7,
          "type": "FLOAT",
          "widget": {
            "name": "noise_aug_strength"
          }
        },
        {
          "label": "latent_strength",
          "name": "latent_strength",
          "shape": 7,
          "type": "FLOAT",
          "widget": {
            "name": "latent_strength"
          }
        }
      ],
      "outputs": [
        {
          "label": "samples",
          "name": "samples",
          "type": "LATENT",
          "links": [
            189
          ]
        }
      ],
      "properties": {
        "Node name for S&R": "WanVideoEncode",
        "widget_ue_connectable": {}
      },
      "widgets_values": [
        false,
        272,
        272,
        144,
        128,
        0,
        1
      ]
    },
    {
      "id": 138,
      "type": "VHS_LoadVideo",
      "pos": [
        883.2557983398438,
        626.9793090820312
      ],
      "size": [
        253.279296875,
        762.71875
      ],
      "flags": {},
      "order": 34,
      "mode": 0,
      "inputs": [
        {
          "label": "meta_batch",
          "name": "meta_batch",
          "shape": 7,
          "type": "VHS_BatchManager"
        },
        {
          "label": "vae",
          "name": "vae",
          "shape": 7,
          "type": "VAE"
        },
        {
          "label": "video",
          "name": "video",
          "type": "STRING",
          "widget": {
            "name": "video"
          }
        },
        {
          "label": "force_rate",
          "name": "force_rate",
          "type": "INT",
          "widget": {
            "name": "force_rate"
          }
        },
        {
          "label": "force_size",
          "name": "force_size",
          "type": "COMBO",
          "widget": {
            "name": "force_size"
          }
        },
        {
          "label": "custom_width",
          "name": "custom_width",
          "type": "INT",
          "widget": {
            "name": "custom_width"
          }
        },
        {
          "label": "custom_height",
          "name": "custom_height",
          "type": "INT",
          "widget": {
            "name": "custom_height"
          }
        },
        {
          "label": "frame_load_cap",
          "name": "frame_load_cap",
          "type": "INT",
          "widget": {
            "name": "frame_load_cap"
          },
          "link": 180
        },
        {
          "label": "skip_first_frames",
          "name": "skip_first_frames",
          "type": "INT",
          "widget": {
            "name": "skip_first_frames"
          }
        },
        {
          "label": "select_every_nth",
          "name": "select_every_nth",
          "type": "INT",
          "widget": {
            "name": "select_every_nth"
          }
        },
        {
          "label": "format",
          "name": "format",
          "shape": 7,
          "type": "COMBO",
          "widget": {
            "name": "format"
          }
        }
      ],
      "outputs": [
        {
          "label": "IMAGE",
          "name": "IMAGE",
          "type": "IMAGE",
          "links": [
            183
          ]
        },
        {
          "label": "frame_count",
          "name": "frame_count",
          "type": "INT"
        },
        {
          "label": "audio",
          "name": "audio",
          "type": "AUDIO"
        },
        {
          "label": "video_info",
          "name": "video_info",
          "type": "VHS_VIDEOINFO"
        }
      ],
      "properties": {
        "Node name for S&R": "VHS_LoadVideo",
        "widget_ue_connectable": {}
      },
      "widgets_values": {
        "video": "c3381ca7aa206d77fdbb1a468a8d58167a5653e41e22b956e11ebadfe4db873b.mp4",
        "force_rate": 0,
        "force_size": "Disabled",
        "custom_width": 0,
        "custom_height": 0,
        "frame_load_cap": 0,
        "skip_first_frames": 0,
        "select_every_nth": 2,
        "format": "AnimateDiff",
        "choose video to upload": "image",
        "videopreview": {
          "paused": false,
          "hidden": false,
          "params": {
            "custom_height": 512,
            "filename": "c3381ca7aa206d77fdbb1a468a8d58167a5653e41e22b956e11ebadfe4db873b.mp4",
            "force_rate": 0,
            "custom_width": 504,
            "select_every_nth": 2,
            "frame_load_cap": 0,
            "format": "video/mp4",
            "skip_first_frames": 0,
            "type": "input"
          }
        }
      }
    }
  ],
  "links": [
    [
      2,
      1,
      0,
      4,
      0,
      "WANVIDEOMODEL"
    ],
    [
      3,
      2,
      0,
      6,
      0,
      "WANTEXTENCODER"
    ],
    [
      27,
      4,
      0,
      29,
      1,
      "LATENT"
    ],
    [
      28,
      3,
      0,
      29,
      0,
      "WANVAE"
    ],
    [
      29,
      29,
      0,
      30,
      0,
      "IMAGE"
    ],
    [
      74,
      51,
      0,
      1,
      1,
      "BLOCKSWAPARGS"
    ],
    [
      138,
      106,
      0,
      108,
      0,
      "IMAGE"
    ],
    [
      159,
      112,
      0,
      108,
      2,
      "INT"
    ],
    [
      160,
      113,
      0,
      108,
      3,
      "INT"
    ],
    [
      168,
      130,
      0,
      1,
      2,
      "WANVIDLORA"
    ],
    [
      169,
      6,
      0,
      4,
      2,
      "WANVIDEOTEXTEMBEDS"
    ],
    [
      175,
      136,
      0,
      135,
      0,
      "WANVIDEOCONTROLNET"
    ],
    [
      177,
      112,
      0,
      141,
      0,
      "*"
    ],
    [
      178,
      113,
      0,
      142,
      0,
      "*"
    ],
    [
      179,
      114,
      0,
      143,
      0,
      "*"
    ],
    [
      180,
      144,
      0,
      138,
      7,
      "INT"
    ],
    [
      181,
      147,
      0,
      146,
      2,
      "INT"
    ],
    [
      182,
      148,
      0,
      146,
      3,
      "INT"
    ],
    [
      183,
      138,
      0,
      146,
      0,
      "IMAGE"
    ],
    [
      184,
      146,
      0,
      149,
      0,
      "IMAGE"
    ],
    [
      185,
      146,
      0,
      150,
      0,
      "*"
    ],
    [
      186,
      3,
      0,
      153,
      0,
      "*"
    ],
    [
      187,
      152,
      0,
      151,
      0,
      "WANVAE"
    ],
    [
      188,
      154,
      0,
      151,
      1,
      "IMAGE"
    ],
    [
      189,
      151,
      0,
      135,
      1,
      "LATENT"
    ],
    [
      190,
      135,
      0,
      4,
      14,
      "UNI3C_EMBEDS"
    ],
    [
      198,
      160,
      0,
      159,
      0,
      "WANVAE"
    ],
    [
      199,
      108,
      0,
      159,
      2,
      "IMAGE"
    ],
    [
      200,
      159,
      0,
      161,
      0,
      "*"
    ],
    [
      201,
      162,
      0,
      4,
      1,
      "WANVIDIMAGE_EMBEDS"
    ],
    [
      203,
      156,
      3,
      159,
      10,
      "INT"
    ],
    [
      204,
      163,
      0,
      156,
      0,
      "IMAGE"
    ],
    [
      205,
      108,
      1,
      159,
      8,
      "INT"
    ],
    [
      206,
      108,
      2,
      159,
      9,
      "INT"
    ],
    [
      207,
      156,
      0,
      169,
      1,
      "IMAGE"
    ],
    [
      208,
      169,
      0,
      159,
      1,
      "WANVIDIMAGE_CLIPEMBEDS"
    ],
    [
      209,
      167,
      0,
      169,
      0,
      "CLIP_VISION"
    ]
  ],
  "groups": [
    {
      "id": 2,
      "title": "采样",
      "bounding": [
        1713.288330078125,
        -480.4558410644531,
        1550.7030029296875,
        968.9901123046875
      ],
      "color": "#3f789e",
      "font_size": 24,
      "flags": {}
    },
    {
      "id": 3,
      "title": "配置",
      "bounding": [
        15.87321662902832,
        -460.3317565917969,
        558.3043212890625,
        429.4057312011719
      ],
      "color": "#3f789e",
      "font_size": 24,
      "flags": {}
    },
    {
      "id": 4,
      "title": "数据处理",
      "bounding": [
        615.33447265625,
        -465.3281555175781,
        1042.613525390625,
        973.0343627929688
      ],
      "color": "#3f789e",
      "font_size": 24,
      "flags": {}
    },
    {
      "id": 5,
      "title": "控制视频",
      "bounding": [
        621.0762329101562,
        542.8628540039062,
        1151.4349365234375,
        868.4215087890625
      ],
      "color": "#3f789e",
      "font_size": 24,
      "flags": {}
    },
    {
      "id": 6,
      "title": "uni3c",
      "bounding": [
        1812.677734375,
        556.2338256835938,
        957.9306640625,
        550.1809692382812
      ],
      "color": "#3f789e",
      "font_size": 24,
      "flags": {}
    }
  ],
  "config": {},
  "extra": {
    "VHS_KeepIntermediate": true,
    "links_added_by_ue": [],
    "VHS_MetadataImage": true,
    "ue_links": [],
    "0246.VERSION": [
      0,
      0,
      4
    ],
    "VHS_latentpreviewrate": 0,
    "VHS_latentpreview": false,
    "frontendVersion": "1.23.0",
    "ds": {
      "scale": 0.20992832109438006,
      "offset": [
        1896.6161255286818,
        1069.8510832525735
      ]
    }
  },
  "version": 0.4
}